snake_shift/__init__.py
snake_shift/cli.py
snake_shift/core.py
snake_shift/file_operations.py
snake_shift/module_detection.py
snake_shift/naming.py
snake_shift/transformer.py
snake_shift-1.0.2.dist-info/METADATA
snake_shift-1.0.2.dist-info/WHEEL
snake_shift-1.0.2.dist-info/entry_points.txt
snake_shift-1.0.2.dist-info/licenses/LICENSE
snake_shift-1.0.2.dist-info/RECORD
