Metadata-Version: 2.4
Name: snake-shift
Version: 1.0.2
Summary: Smart codebase refactor from camelCase to pythonic snake_case
Project-URL: Homepage, https://github.com/simondoesstuff/snake_shift
Project-URL: Repository, https://github.com/simondoesstuff/snake_shift
Project-URL: Issues, https://github.com/simondoesstuff/snake_shift/issues
Author-email: Simon Walker <simon@simonwalker.tech>
License-Expression: MIT
License-File: LICENSE
Keywords: camelcase,code-formatting,python,refactoring,snake-case
Classifier: Development Status :: 5 - Production/Stable
Classifier: Intended Audience :: Developers
Classifier: License :: OSI Approved :: MIT License
Classifier: Programming Language :: Python :: 3
Classifier: Programming Language :: Python :: 3.9
Classifier: Programming Language :: Python :: 3.10
Classifier: Programming Language :: Python :: 3.11
Classifier: Programming Language :: Python :: 3.12
Classifier: Programming Language :: Python :: 3.13
Classifier: Topic :: Software Development :: Code Generators
Classifier: Topic :: Software Development :: Libraries :: Python Modules
Classifier: Topic :: Utilities
Requires-Python: >=3.9
Requires-Dist: libcst>=1.8.2
Requires-Dist: rich>=13.0.0
Requires-Dist: typer>=0.16.1
